.codecov.yml
.coveragerc
.flake8
.gitignore
AUTHORS.txt
CHANGELOG.rst
INSTALLATION.txt
LICENSE
MANIFEST.in
README.md
docBuildInstructions.txt
github_deploy_key.enc
requirements-dev.txt
requirements-docs.txt
requirements.txt
rever.xsh
run_tests.py
setup.py
.github/workflows/docs.yml
.github/workflows/test.yml
docs/Makefile
docs/conf.py
docs/index.rst
docs/installation.rst
docs/make.bat
docs/xpdsim.data.XPD.rst
docs/xpdsim.data.rst
docs/xpdsim.rst
docs/xpdsim.tests.rst
news/TEMPLATE
xpdsim/__init__.py
xpdsim/area_det.py
xpdsim/movers.py
xpdsim.egg-info/PKG-INFO
xpdsim.egg-info/SOURCES.txt
xpdsim.egg-info/dependency_links.txt
xpdsim.egg-info/not-zip-safe
xpdsim.egg-info/top_level.txt
xpdsim/data/__init__.py
xpdsim/data/XPD/__init__.py
xpdsim/data/XPD/ni/sub_20170626-150911_Ni_Tim_series_tseries_1_e910af_0250.tif
xpdsim/data/chess/CeO2_ff_07365.tif
xpdsim/data/chess/Ni_stdr_fullDet_darkSub.tif
xpdsim/data/chess/Si_2min_darkSub_07017.tif
xpdsim/data/pyfai/pyFAI_calib.yml
xpdsim/data/pyfai/test.poni
xpdsim/tests/__init__.py
xpdsim/tests/conftest.py
xpdsim/tests/test_dets.py
xpdsim/tests/test_imports.py
xpdsim/tests/test_movers.py