Metadata-Version: 2.1
Name: xpdsim
Version: 0.4.3
Summary: simulators
Home-page: https://github.com/xpdAcq/xpdSim
License: UNKNOWN
Platform: UNKNOWN
License-File: LICENSE
License-File: AUTHORS.txt
